mwdumps/__init__.py
mwdumps/cmdline.py
mwdumps/config.py
mwdumps/downloader.py
mwdumps/dump.py
mwdumps/dumpmetadata.py
mwdumps/errors.py
mwdumps-0.2.dist-info/DESCRIPTION.rst
mwdumps-0.2.dist-info/METADATA
mwdumps-0.2.dist-info/RECORD
mwdumps-0.2.dist-info/WHEEL
mwdumps-0.2.dist-info/entry_points.txt
mwdumps-0.2.dist-info/metadata.json
mwdumps-0.2.dist-info/top_level.txt
