Metadata-Version: 2.0
Name: mwdumps
Version: 0.2
Summary: A utility for downloading Wikimedia dumps
Home-page: https://github.com/kjschiroo/python-mwdumps
Author: Kevin Schiroo
Author-email: kjschiroo@gmail.com
License: MIT
Platform: UNKNOWN
Classifier: Programming Language :: Python :: 3
Classifier: Programming Language :: Python :: 3 :: Only
Classifier: Intended Audience :: Developers
Classifier: License :: OSI Approved :: MIT License
Classifier: Topic :: Utilities
Requires-Dist: docopt
Requires-Dist: beautifulsoup4
Requires-Dist: python-dateutil
Requires-Dist: requests
